pcsg/__init__.py
pcsg/algorithms.py
pcsg/animation.py
pcsg/attributeTypes.py
pcsg/attributes.py
pcsg/boolean.py
pcsg/constants.py
pcsg/immutable.py
pcsg/shape.py
pcsg/solid.py
pcsg/tool.py
pcsg/transform.py
pcsg/tree.py
pcsg/construction/__init__.py
pcsg/construction/gear.py
pcsg/util/__init__.py
pcsg/util/cache.py
pcsg/util/commandline.py
pcsg/util/differentialdrawing.py
pcsg/util/downsample.py
pcsg/util/encoder.py
pcsg/util/hash.py
pcsg/util/materializer.py
pcsg/util/matrix.py
pcsg/util/parallel.py
pcsg/util/polytool.py
pcsg/util/random.py
pcsg/util/textwriter.py
pcsg/util/vmath.py
pcsg/util/external/__init__.py
pcsg/util/external/openscad.py
pcsg/util/external/povray.py
pcsg-0.0.3.dist-info/LICENSE
pcsg-0.0.3.dist-info/METADATA
pcsg-0.0.3.dist-info/WHEEL
pcsg-0.0.3.dist-info/top_level.txt
pcsg-0.0.3.dist-info/RECORD
