Metadata-Version: 2.1
Name: pcsg
Version: 0.0.3
Summary: A constructive solid geometry library for Python
Home-page: https://github.com/WhiteSheet/pcsg
Author: Julian Dessecker
License: UNKNOWN
Platform: UNKNOWN
Classifier: Programming Language :: Python :: 3
Classifier: License :: OSI Approved :: MIT License
Classifier: Operating System :: OS Independent
Requires-Python: >=3.8
